db.py
main.py
notes_semantic_db.py
utils.py
notes_app_cli-0.1.1.dist-info/METADATA
notes_app_cli-0.1.1.dist-info/WHEEL
notes_app_cli-0.1.1.dist-info/entry_points.txt
notes_app_cli-0.1.1.dist-info/top_level.txt
notes_app_cli-0.1.1.dist-info/RECORD
