Metadata-Version: 2.4
Name: notes-app-cli
Version: 0.1.1
Summary: A CLI tool for adding and reviewing notes
Author: Tejaaswini
Requires-Python: >=3.7
Requires-Dist: rich>=10.0.0
Requires-Dist: questionary>=2.0.0
Requires-Dist: chromadb
Requires-Dist: sentence-transformers
Dynamic: author
Dynamic: description
Dynamic: description-content-type
Dynamic: requires-dist
Dynamic: requires-python
Dynamic: summary
